pytest_requests_futures/__init__.py
pytest_requests_futures/fixtures.py
pytest_requests_futures-0.9.0.dist-info/LICENSE
pytest_requests_futures-0.9.0.dist-info/METADATA
pytest_requests_futures-0.9.0.dist-info/WHEEL
pytest_requests_futures-0.9.0.dist-info/entry_points.txt
pytest_requests_futures-0.9.0.dist-info/top_level.txt
pytest_requests_futures-0.9.0.dist-info/RECORD
