Metadata-Version: 2.1
Name: pytest-requests-futures
Version: 0.9.0
Summary: Pytest Plugin to Mock Requests Futures
Home-page: https://github.com/boromir674/pytest-requests-futures
Download-URL: https://github.com/boromir674/pytest-requests-futures/archive/v0.9.0.tar.gz
Author: Konstantinos Lampridis
Author-email: k.lampridis@hotmail.com
Maintainer: Konstantinos Lampridis
Maintainer-email: k.lampridis@hotmail.com
License: AGPL-3.0-only
Project-URL: Documentation, https://pytest-requests-futures.readthedocs.io/
Project-URL: CI: Github Actions, https://github.com/boromir674/pytest-requests-futures/actions
Project-URL: Bug Tracker, https://github.com/pytest-requests-futures/issues
Project-URL: Source Code, https://github.com/boromir674/pytest-requests-futures
Project-URL: Changelog, https://github.com/boromir674/pytest-requests-futures/blob/master/CHANGELOG.rst
Project-URL: Code of Conduct, https://github.com/boromir674/pytest-requests-futures/blob/master/CONTRIBUTING.rst
Keywords: python package
Platform: All
Classifier: Development Status :: 5 - Production/Stable
Classifier: Intended Audience :: Developers
Classifier: Intended Audience :: End Users/Desktop
Classifier: Intended Audience :: Science/Research
Classifier: License :: OSI Approved :: GNU Affero General Public License v3
Classifier: Natural Language :: English
Classifier: Operating System :: Unix
Classifier: Programming Language :: Python
Classifier: Programming Language :: Python :: 3.6
Classifier: Programming Language :: Python :: 3.7
Classifier: Programming Language :: Python :: 3.8
Classifier: Programming Language :: Python :: 3.9
Classifier: Programming Language :: Python :: 3.10
Classifier: Topic :: Software Development
Classifier: Topic :: Software Development :: Libraries :: Python Modules
Classifier: Topic :: System :: Software Distribution
Classifier: Typing :: Typed
Requires-Python: >3.6
License-File: LICENSE
Requires-Dist: pytest
Provides-Extra: docs
Requires-Dist: furo (>=2021.08.31) ; extra == 'docs'
Requires-Dist: sphinx (~=4.0) ; extra == 'docs'
Requires-Dist: sphinx-autodoc-typehints (>=1.10) ; extra == 'docs'
Requires-Dist: sphinxcontrib-spelling (~=7.3.3) ; extra == 'docs'
Requires-Dist: sphinx-rtd-theme (==0.5.0) ; extra == 'docs'
Provides-Extra: test
Requires-Dist: pytest (>=6.2.4) ; extra == 'test'
Requires-Dist: pytest-cov (>=2.12) ; extra == 'test'
Requires-Dist: pytest-xdist (>=1.34) ; extra == 'test'
Requires-Dist: pytest-run-subprocess (~=0.9.0) ; extra == 'test'
Requires-Dist: ask-pypi ; extra == 'test'
Provides-Extra: typing
Requires-Dist: mypy ; extra == 'typing'
